pyPrimeV2/__init__.py
pyPrimeV2-0.1.dist-info/LICENSE.txt
pyPrimeV2-0.1.dist-info/METADATA
pyPrimeV2-0.1.dist-info/WHEEL
pyPrimeV2-0.1.dist-info/top_level.txt
pyPrimeV2-0.1.dist-info/RECORD
